package.json
libspu/py.typed
libspu/spu_pb2.pyi
spu_stubs-0.0.1.dev0.dist-info/METADATA
spu_stubs-0.0.1.dev0.dist-info/WHEEL
spu_stubs-0.0.1.dev0.dist-info/RECORD
